screen_object_detector/__init__.py
screen_object_detector/cli.py
screen_object_detector/json_handler.py
screen_object_detector/screen_detector.py
screen_object_detector-1.0.2.dist-info/METADATA
screen_object_detector-1.0.2.dist-info/WHEEL
screen_object_detector-1.0.2.dist-info/entry_points.txt
screen_object_detector-1.0.2.dist-info/top_level.txt
screen_object_detector-1.0.2.dist-info/RECORD
