Metadata-Version: 2.4
Name: screen-object-detector
Version: 1.0.2
Summary: Real-time object detection on screen using YOLO models
Author: Jester
Author-email: thettboy11@gmail.com
Requires-Python: >=3.8
Requires-Dist: ultralytics>=8.0.0
Requires-Dist: opencv-python>=4.8.0
Requires-Dist: numpy>=1.21.0
Requires-Dist: mss>=6.1.0
Requires-Dist: pillow>=9.0.0
Dynamic: author
Dynamic: author-email
Dynamic: requires-dist
Dynamic: requires-python
Dynamic: summary
